[
    {
        "id": 1,
        "question": "What country does this flag belong to?",
        "flag": "https://www.countryflags.io/AD/flat/64.png",
        "optionOne": "Benin",
        "optionTwo": "Andorra",
        "optionThree": "Montserrat",
        "optionFour": "Isle of Man",
        "correctAnswer": 2
    },
    {
        "id": 2,
        "question": "What country does this flag belong to?",
        "flag": "https://www.countryflags.io/AE/flat/64.png",
        "optionOne": "Nauru",
        "optionTwo": "Mali",
        "optionThree": "Bahamas",
        "optionFour": "United Arab Emirates",
        "correctAnswer": 4
    },
    {
        "id": 3,
        "question": "What country does this flag belong to?",
        "flag": "https://www.countryflags.io/AF/flat/64.png",
        "optionOne": "Afghanistan",
        "optionTwo": "Bermuda",
        "optionThree": "Netherlands Antilles",
        "optionFour": "Cook Islands",
        "correctAnswer": 1
    },
    {
        "id": 4,
        "question": "What country does this flag belong to?",
        "flag": "https://www.countryflags.io/AG/flat/64.png",
        "optionOne": "Malta",
        "optionTwo": "Antigua and Barbuda",
        "optionThree": "Central African Republic",
        "optionFour": "Saint Lucia",
        "correctAnswer": 2
    },
    {
        "id": 5,
        "question": "What country does this flag belong to?",
        "flag": "https://www.countryflags.io/AI/flat/64.png",
        "optionOne": "Benin",
        "optionTwo": "Anguilla",
        "optionThree": "Ecuador",
        "optionFour": "Jordan",
        "correctAnswer": 2
    },
    {
        "id": 6,
        "question": "What country does this flag belong to?",
        "flag": "https://www.countryflags.io/AL/flat/64.png",
        "optionOne": "Bolivia",
        "optionTwo": "Albania",
        "optionThree": "Luxembourg",
        "optionFour": "Mozambique",
        "correctAnswer": 2
    },
    {
        "id": 7,
        "question": "What country does this flag belong to?",
        "flag": "https://www.countryflags.io/AM/flat/64.png",
        "optionOne": "Armenia",
        "optionTwo": "Antarctica",
        "optionThree": "Jersey",
        "optionFour": "Nepal",
        "correctAnswer": 1
    },
    {
        "id": 8,
        "question": "What country does this flag belong to?",
        "flag": "https://www.countryflags.io/AN/flat/64.png",
        "optionOne": "Bosnia and Herzegovina",
        "optionTwo": "Antarctica",
        "optionThree": "Ireland",
        "optionFour": "Netherlands Antilles",
        "correctAnswer": 4
    },
    {
        "id": 9,
        "question": "What country does this flag belong to?",
        "flag": "https://www.countryflags.io/AO/flat/64.png",
        "optionOne": "Angola",
        "optionTwo": "Niger",
        "optionThree": "Saint Martin",
        "optionFour": "Congo, The Democratic Republic Of The",
        "correctAnswer": 1
    },
    {
        "id": 10,
        "question": "What country does this flag belong to?",
        "flag": "https://www.countryflags.io/AQ/flat/64.png",
        "optionOne": "Benin",
        "optionTwo": "Antarctica",
        "optionThree": "Kenya",
        "optionFour": "Congo",
        "correctAnswer": 2
    },
    {
        "id": 11,
        "question": "What country does this flag belong to?",
        "flag": "https://www.countryflags.io/AR/flat/64.png",
        "optionOne": "Argentina",
        "optionTwo": "Ireland",
        "optionThree": "Ecuador",
        "optionFour": "Iceland",
        "correctAnswer": 1
    },
    {
        "id": 12,
        "question": "What country does this flag belong to?",
        "flag": "https://www.countryflags.io/AS/flat/64.png",
        "optionOne": "Afghanistan",
        "optionTwo": "American Samoa",
        "optionThree": "Latvia",
        "optionFour": "Iceland",
        "correctAnswer": 2
    },
    {
        "id": 13,
        "question": "What country does this flag belong to?",
        "flag": "https://www.countryflags.io/AT/flat/64.png",
        "optionOne": "Austria",
        "optionTwo": "Libya",
        "optionThree": "Brazil",
        "optionFour": "Botswana",
        "correctAnswer": 1
    },
    {
        "id": 14,
        "question": "What country does this flag belong to?",
        "flag": "https://www.countryflags.io/AU/flat/64.png",
        "optionOne": "Macao",
        "optionTwo": "Cape Verde",
        "optionThree": "Australia",
        "optionFour": "Luxembourg",
        "correctAnswer": 3
    },
    {
        "id": 15,
        "question": "What country does this flag belong to?",
        "flag": "https://www.countryflags.io/AW/flat/64.png",
        "optionOne": "Ireland",
        "optionTwo": "Marshall Islands",
        "optionThree": "Aruba",
        "optionFour": "Cape Verde",
        "correctAnswer": 3
    },
    {
        "id": 16,
        "question": "What country does this flag belong to?",
        "flag": "https://www.countryflags.io/AX/flat/64.png",
        "optionOne": "Algeria",
        "optionTwo": "\u00c3\u2026land Islands",
        "optionThree": "Zimbabwe",
        "optionFour": "Bouvet Island",
        "correctAnswer": 2
    },
    {
        "id": 17,
        "question": "What country does this flag belong to?",
        "flag": "https://www.countryflags.io/AZ/flat/64.png",
        "optionOne": "Iraq",
        "optionTwo": "Belize",
        "optionThree": "Azerbaijan",
        "optionFour": "Belarus",
        "correctAnswer": 3
    },
    {
        "id": 18,
        "question": "What country does this flag belong to?",
        "flag": "https://www.countryflags.io/BA/flat/64.png",
        "optionOne": "Saint Lucia",
        "optionTwo": "Bangladesh",
        "optionThree": "Bosnia and Herzegovina",
        "optionFour": "Canada",
        "correctAnswer": 3
    },
    {
        "id": 19,
        "question": "What country does this flag belong to?",
        "flag": "https://www.countryflags.io/BB/flat/64.png",
        "optionOne": "Japan",
        "optionTwo": "Barbados",
        "optionThree": "Korea, Republic of",
        "optionFour": "Austria",
        "correctAnswer": 2
    },
    {
        "id": 20,
        "question": "What country does this flag belong to?",
        "flag": "https://www.countryflags.io/BD/flat/64.png",
        "optionOne": "Argentina",
        "optionTwo": "Colombia",
        "optionThree": "Kyrgyzstan",
        "optionFour": "Bangladesh",
        "correctAnswer": 4
    },
    {
        "id": 21,
        "question": "What country does this flag belong to?",
        "flag": "https://www.countryflags.io/BE/flat/64.png",
        "optionOne": "Belgium",
        "optionTwo": "Benin",
        "optionThree": "Niue",
        "optionFour": "Bouvet Island",
        "correctAnswer": 1
    },
    {
        "id": 22,
        "question": "What country does this flag belong to?",
        "flag": "https://www.countryflags.io/BF/flat/64.png",
        "optionOne": "C\u00c3\u00b4te D'Ivoire",
        "optionTwo": "Bhutan",
        "optionThree": "Burkina Faso",
        "optionFour": "New Caledonia",
        "correctAnswer": 3
    },
    {
        "id": 23,
        "question": "What country does this flag belong to?",
        "flag": "https://www.countryflags.io/BG/flat/64.png",
        "optionOne": "Bhutan",
        "optionTwo": "Czech Republic",
        "optionThree": "Bahamas",
        "optionFour": "Bulgaria",
        "correctAnswer": 4
    },
    {
        "id": 24,
        "question": "What country does this flag belong to?",
        "flag": "https://www.countryflags.io/BH/flat/64.png",
        "optionOne": "Bahrain",
        "optionTwo": "Luxembourg",
        "optionThree": "Saint Barth\u00c3\u00a9lemy",
        "optionFour": "South Africa",
        "correctAnswer": 1
    },
    {
        "id": 25,
        "question": "What country does this flag belong to?",
        "flag": "https://www.countryflags.io/BI/flat/64.png",
        "optionOne": "Maldives",
        "optionTwo": "Burundi",
        "optionThree": "Iran, Islamic Republic Of",
        "optionFour": "Azerbaijan",
        "correctAnswer": 2
    },
    {
        "id": 26,
        "question": "What country does this flag belong to?",
        "flag": "https://www.countryflags.io/BJ/flat/64.png",
        "optionOne": "Nepal",
        "optionTwo": "Anguilla",
        "optionThree": "Saint Barth\u00c3\u00a9lemy",
        "optionFour": "Benin",
        "correctAnswer": 4
    },
    {
        "id": 27,
        "question": "What country does this flag belong to?",
        "flag": "https://www.countryflags.io/BL/flat/64.png",
        "optionOne": "Madagascar",
        "optionTwo": "Jersey",
        "optionThree": "Austria",
        "optionFour": "Saint Barth\u00c3\u00a9lemy",
        "correctAnswer": 4
    },
    {
        "id": 28,
        "question": "What country does this flag belong to?",
        "flag": "https://www.countryflags.io/BM/flat/64.png",
        "optionOne": "Congo, The Democratic Republic Of The",
        "optionTwo": "Bermuda",
        "optionThree": "Yemen",
        "optionFour": "Antarctica",
        "correctAnswer": 2
    },
    {
        "id": 29,
        "question": "What country does this flag belong to?",
        "flag": "https://www.countryflags.io/BN/flat/64.png",
        "optionOne": "Brunei Darussalam",
        "optionTwo": "Namibia",
        "optionThree": "Korea, Republic of",
        "optionFour": "Kuwait",
        "correctAnswer": 1
    },
    {
        "id": 30,
        "question": "What country does this flag belong to?",
        "flag": "https://www.countryflags.io/BO/flat/64.png",
        "optionOne": "Barbados",
        "optionTwo": "Bolivia",
        "optionThree": "Congo, The Democratic Republic Of The",
        "optionFour": "Djibouti",
        "correctAnswer": 2
    },
    {
        "id": 31,
        "question": "What country does this flag belong to?",
        "flag": "https://www.countryflags.io/BQ/flat/64.png",
        "optionOne": "Bonaire, Sint Eustatius and Saba",
        "optionTwo": "Ecuador",
        "optionThree": "Djibouti",
        "optionFour": "Czech Republic",
        "correctAnswer": 1
    },
    {
        "id": 32,
        "question": "What country does this flag belong to?",
        "flag": "https://www.countryflags.io/BR/flat/64.png",
        "optionOne": "Cape Verde",
        "optionTwo": "Isle of Man",
        "optionThree": "Christmas Island",
        "optionFour": "Brazil",
        "correctAnswer": 4
    },
    {
        "id": 33,
        "question": "What country does this flag belong to?",
        "flag": "https://www.countryflags.io/BS/flat/64.png",
        "optionOne": "Malta",
        "optionTwo": "Netherlands",
        "optionThree": "Cambodia",
        "optionFour": "Bahamas",
        "correctAnswer": 4
    },
    {
        "id": 34,
        "question": "What country does this flag belong to?",
        "flag": "https://www.countryflags.io/BT/flat/64.png",
        "optionOne": "Martinique",
        "optionTwo": "Malawi",
        "optionThree": "Bhutan",
        "optionFour": "Liberia",
        "correctAnswer": 3
    },
    {
        "id": 35,
        "question": "What country does this flag belong to?",
        "flag": "https://www.countryflags.io/BV/flat/64.png",
        "optionOne": "Macedonia, the Former Yugoslav Republic Of",
        "optionTwo": "Czech Republic",
        "optionThree": "Bouvet Island",
        "optionFour": "Jamaica",
        "correctAnswer": 3
    },
    {
        "id": 36,
        "question": "What country does this flag belong to?",
        "flag": "https://www.countryflags.io/BW/flat/64.png",
        "optionOne": "Colombia",
        "optionTwo": "Botswana",
        "optionThree": "Bermuda",
        "optionFour": "Andorra",
        "correctAnswer": 2
    },
    {
        "id": 37,
        "question": "What country does this flag belong to?",
        "flag": "https://www.countryflags.io/BY/flat/64.png",
        "optionOne": "Belarus",
        "optionTwo": "Botswana",
        "optionThree": "Martinique",
        "optionFour": "Zimbabwe",
        "correctAnswer": 1
    },
    {
        "id": 38,
        "question": "What country does this flag belong to?",
        "flag": "https://www.countryflags.io/BZ/flat/64.png",
        "optionOne": "Bhutan",
        "optionTwo": "Belize",
        "optionThree": "Nigeria",
        "optionFour": "Iceland",
        "correctAnswer": 2
    },
    {
        "id": 39,
        "question": "What country does this flag belong to?",
        "flag": "https://www.countryflags.io/CA/flat/64.png",
        "optionOne": "Lebanon",
        "optionTwo": "Armenia",
        "optionThree": "Western Sahara",
        "optionFour": "Canada",
        "correctAnswer": 4
    },
    {
        "id": 40,
        "question": "What country does this flag belong to?",
        "flag": "https://www.countryflags.io/CC/flat/64.png",
        "optionOne": "Egypt",
        "optionTwo": "Cocos (Keeling) Islands",
        "optionThree": "Korea, Democratic People's Republic Of",
        "optionFour": "Belarus",
        "correctAnswer": 2
    },
    {
        "id": 41,
        "question": "What country does this flag belong to?",
        "flag": "https://www.countryflags.io/CD/flat/64.png",
        "optionOne": "Colombia",
        "optionTwo": "Congo, The Democratic Republic Of The",
        "optionThree": "Macedonia, the Former Yugoslav Republic Of",
        "optionFour": "Bangladesh",
        "correctAnswer": 2
    },
    {
        "id": 42,
        "question": "What country does this flag belong to?",
        "flag": "https://www.countryflags.io/CF/flat/64.png",
        "optionOne": "Colombia",
        "optionTwo": "Ecuador",
        "optionThree": "Central African Republic",
        "optionFour": "Liberia",
        "correctAnswer": 3
    },
    {
        "id": 43,
        "question": "What country does this flag belong to?",
        "flag": "https://www.countryflags.io/CG/flat/64.png",
        "optionOne": "Congo",
        "optionTwo": "Martinique",
        "optionThree": "Bouvet Island",
        "optionFour": "Niue",
        "correctAnswer": 1
    },
    {
        "id": 44,
        "question": "What country does this flag belong to?",
        "flag": "https://www.countryflags.io/CH/flat/64.png",
        "optionOne": "Cambodia",
        "optionTwo": "Switzerland",
        "optionThree": "Indonesia",
        "optionFour": "Algeria",
        "correctAnswer": 2
    },
    {
        "id": 45,
        "question": "What country does this flag belong to?",
        "flag": "https://www.countryflags.io/CI/flat/64.png",
        "optionOne": "Latvia",
        "optionTwo": "Lao People's Democratic Republic",
        "optionThree": "Libya",
        "optionFour": "C\u00c3\u00b4te D'Ivoire",
        "correctAnswer": 4
    },
    {
        "id": 46,
        "question": "What country does this flag belong to?",
        "flag": "https://www.countryflags.io/CK/flat/64.png",
        "optionOne": "Estonia",
        "optionTwo": "Myanmar",
        "optionThree": "Northern Mariana Islands",
        "optionFour": "Cook Islands",
        "correctAnswer": 4
    },
    {
        "id": 47,
        "question": "What country does this flag belong to?",
        "flag": "https://www.countryflags.io/CL/flat/64.png",
        "optionOne": "Chile",
        "optionTwo": "Northern Mariana Islands",
        "optionThree": "Central African Republic",
        "optionFour": "Netherlands",
        "correctAnswer": 1
    },
    {
        "id": 48,
        "question": "What country does this flag belong to?",
        "flag": "https://www.countryflags.io/CM/flat/64.png",
        "optionOne": "Austria",
        "optionTwo": "Czech Republic",
        "optionThree": "Cameroon",
        "optionFour": "Switzerland",
        "correctAnswer": 3
    },
    {
        "id": 49,
        "question": "What country does this flag belong to?",
        "flag": "https://www.countryflags.io/CN/flat/64.png",
        "optionOne": "Armenia",
        "optionTwo": "Mauritania",
        "optionThree": "China",
        "optionFour": "Nepal",
        "correctAnswer": 3
    },
    {
        "id": 50,
        "question": "What country does this flag belong to?",
        "flag": "https://www.countryflags.io/CO/flat/64.png",
        "optionOne": "Japan",
        "optionTwo": "Iraq",
        "optionThree": "Colombia",
        "optionFour": "Iran, Islamic Republic Of",
        "correctAnswer": 3
    },
    {
        "id": 51,
        "question": "What country does this flag belong to?",
        "flag": "https://www.countryflags.io/CR/flat/64.png",
        "optionOne": "Israel",
        "optionTwo": "Armenia",
        "optionThree": "Madagascar",
        "optionFour": "Costa Rica",
        "correctAnswer": 4
    },
    {
        "id": 52,
        "question": "What country does this flag belong to?",
        "flag": "https://www.countryflags.io/CU/flat/64.png",
        "optionOne": "Colombia",
        "optionTwo": "Liberia",
        "optionThree": "Cuba",
        "optionFour": "Netherlands",
        "correctAnswer": 3
    },
    {
        "id": 53,
        "question": "What country does this flag belong to?",
        "flag": "https://www.countryflags.io/CV/flat/64.png",
        "optionOne": "Cape Verde",
        "optionTwo": "Moldova, Republic of",
        "optionThree": "Brunei Darussalam",
        "optionFour": "Germany",
        "correctAnswer": 1
    },
    {
        "id": 54,
        "question": "What country does this flag belong to?",
        "flag": "https://www.countryflags.io/CW/flat/64.png",
        "optionOne": "Saint Lucia",
        "optionTwo": "Netherlands Antilles",
        "optionThree": "Benin",
        "optionFour": "Cura\u00c3\u00a7ao",
        "correctAnswer": 4
    },
    {
        "id": 55,
        "question": "What country does this flag belong to?",
        "flag": "https://www.countryflags.io/CX/flat/64.png",
        "optionOne": "Denmark",
        "optionTwo": "Christmas Island",
        "optionThree": "Montenegro",
        "optionFour": "Ecuador",
        "correctAnswer": 2
    },
    {
        "id": 56,
        "question": "What country does this flag belong to?",
        "flag": "https://www.countryflags.io/CY/flat/64.png",
        "optionOne": "Nauru",
        "optionTwo": "Bouvet Island",
        "optionThree": "Cyprus",
        "optionFour": "Nigeria",
        "correctAnswer": 3
    },
    {
        "id": 57,
        "question": "What country does this flag belong to?",
        "flag": "https://www.countryflags.io/CZ/flat/64.png",
        "optionOne": "Yemen",
        "optionTwo": "Estonia",
        "optionThree": "Kyrgyzstan",
        "optionFour": "Czech Republic",
        "correctAnswer": 4
    },
    {
        "id": 58,
        "question": "What country does this flag belong to?",
        "flag": "https://www.countryflags.io/DE/flat/64.png",
        "optionOne": "Germany",
        "optionTwo": "Montenegro",
        "optionThree": "Ireland",
        "optionFour": "Mozambique",
        "correctAnswer": 1
    },
    {
        "id": 59,
        "question": "What country does this flag belong to?",
        "flag": "https://www.countryflags.io/DJ/flat/64.png",
        "optionOne": "Djibouti",
        "optionTwo": "Armenia",
        "optionThree": "Bermuda",
        "optionFour": "Malaysia",
        "correctAnswer": 1
    },
    {
        "id": 60,
        "question": "What country does this flag belong to?",
        "flag": "https://www.countryflags.io/DK/flat/64.png",
        "optionOne": "Denmark",
        "optionTwo": "Barbados",
        "optionThree": "Afghanistan",
        "optionFour": "Bosnia and Herzegovina",
        "correctAnswer": 1
    },
    {
        "id": 61,
        "question": "What country does this flag belong to?",
        "flag": "https://www.countryflags.io/DM/flat/64.png",
        "optionOne": "Dominica",
        "optionTwo": "Cameroon",
        "optionThree": "Austria",
        "optionFour": "Cambodia",
        "correctAnswer": 1
    },
    {
        "id": 62,
        "question": "What country does this flag belong to?",
        "flag": "https://www.countryflags.io/DO/flat/64.png",
        "optionOne": "Cayman Islands",
        "optionTwo": "Germany",
        "optionThree": "Luxembourg",
        "optionFour": "Dominican Republic",
        "correctAnswer": 4
    },
    {
        "id": 63,
        "question": "What country does this flag belong to?",
        "flag": "https://www.countryflags.io/DZ/flat/64.png",
        "optionOne": "Algeria",
        "optionTwo": "Djibouti",
        "optionThree": "Martinique",
        "optionFour": "Mozambique",
        "correctAnswer": 1
    },
    {
        "id": 64,
        "question": "What country does this flag belong to?",
        "flag": "https://www.countryflags.io/EC/flat/64.png",
        "optionOne": "Martinique",
        "optionTwo": "Christmas Island",
        "optionThree": "Belarus",
        "optionFour": "Ecuador",
        "correctAnswer": 4
    },
    {
        "id": 65,
        "question": "What country does this flag belong to?",
        "flag": "https://www.countryflags.io/EE/flat/64.png",
        "optionOne": "Mexico",
        "optionTwo": "Estonia",
        "optionThree": "Liechtenstein",
        "optionFour": "Angola",
        "correctAnswer": 2
    },
    {
        "id": 66,
        "question": "What country does this flag belong to?",
        "flag": "https://www.countryflags.io/EG/flat/64.png",
        "optionOne": "Egypt",
        "optionTwo": "Namibia",
        "optionThree": "Lesotho",
        "optionFour": "Mali",
        "correctAnswer": 1
    },
    {
        "id": 67,
        "question": "What country does this flag belong to?",
        "flag": "https://www.countryflags.io/EH/flat/64.png",
        "optionOne": "Macao",
        "optionTwo": "Western Sahara",
        "optionThree": "Western Sahara",
        "optionFour": "Czech Republic",
        "correctAnswer": 3
    },
    {
        "id": 68,
        "question": "What country does this flag belong to?",
        "flag": "https://www.countryflags.io/ER/flat/64.png",
        "optionOne": "Bhutan",
        "optionTwo": "Bolivia",
        "optionThree": "Eritrea",
        "optionFour": "Czech Republic",
        "correctAnswer": 3
    },
    {
        "id": 69,
        "question": "What country does this flag belong to?",
        "flag": "https://www.countryflags.io/ES/flat/64.png",
        "optionOne": "Spain",
        "optionTwo": "Myanmar",
        "optionThree": "Argentina",
        "optionFour": "Spain",
        "correctAnswer": 1
    },
    {
        "id": 70,
        "question": "What country does this flag belong to?",
        "flag": "https://www.countryflags.io/ET/flat/64.png",
        "optionOne": "Antigua and Barbuda",
        "optionTwo": "Malaysia",
        "optionThree": "Albania",
        "optionFour": "Ethiopia",
        "correctAnswer": 4
    },
    {
        "id": 71,
        "question": "What country does this flag belong to?",
        "flag": "https://www.countryflags.io/ID/flat/64.png",
        "optionOne": "Congo",
        "optionTwo": "Macedonia, the Former Yugoslav Republic Of",
        "optionThree": "Indonesia",
        "optionFour": "Czech Republic",
        "correctAnswer": 3
    },
    {
        "id": 72,
        "question": "What country does this flag belong to?",
        "flag": "https://www.countryflags.io/IE/flat/64.png",
        "optionOne": "Central African Republic",
        "optionTwo": "Ireland",
        "optionThree": "Congo",
        "optionFour": "Martinique",
        "correctAnswer": 2
    },
    {
        "id": 73,
        "question": "What country does this flag belong to?",
        "flag": "https://www.countryflags.io/IL/flat/64.png",
        "optionOne": "Bahrain",
        "optionTwo": "Namibia",
        "optionThree": "Armenia",
        "optionFour": "Israel",
        "correctAnswer": 4
    },
    {
        "id": 74,
        "question": "What country does this flag belong to?",
        "flag": "https://www.countryflags.io/IM/flat/64.png",
        "optionOne": "Argentina",
        "optionTwo": "Myanmar",
        "optionThree": "Cayman Islands",
        "optionFour": "Isle of Man",
        "correctAnswer": 4
    },
    {
        "id": 75,
        "question": "What country does this flag belong to?",
        "flag": "https://www.countryflags.io/IN/flat/64.png",
        "optionOne": "India",
        "optionTwo": "Italy",
        "optionThree": "Malawi",
        "optionFour": "Benin",
        "correctAnswer": 1
    },
    {
        "id": 76,
        "question": "What country does this flag belong to?",
        "flag": "https://www.countryflags.io/IO/flat/64.png",
        "optionOne": "Barbados",
        "optionTwo": "British Indian Ocean Territory",
        "optionThree": "Madagascar",
        "optionFour": "Antigua and Barbuda",
        "correctAnswer": 2
    },
    {
        "id": 77,
        "question": "What country does this flag belong to?",
        "flag": "https://www.countryflags.io/IQ/flat/64.png",
        "optionOne": "Iraq",
        "optionTwo": "Cuba",
        "optionThree": "Lao People's Democratic Republic",
        "optionFour": "Malaysia",
        "correctAnswer": 1
    },
    {
        "id": 78,
        "question": "What country does this flag belong to?",
        "flag": "https://www.countryflags.io/IR/flat/64.png",
        "optionOne": "Saint Barth\u00c3\u00a9lemy",
        "optionTwo": "Benin",
        "optionThree": "Namibia",
        "optionFour": "Iran, Islamic Republic Of",
        "correctAnswer": 4
    },
    {
        "id": 79,
        "question": "What country does this flag belong to?",
        "flag": "https://www.countryflags.io/IS/flat/64.png",
        "optionOne": "Australia",
        "optionTwo": "Ireland",
        "optionThree": "Mali",
        "optionFour": "Iceland",
        "correctAnswer": 4
    },
    {
        "id": 80,
        "question": "What country does this flag belong to?",
        "flag": "https://www.countryflags.io/IT/flat/64.png",
        "optionOne": "Bahamas",
        "optionTwo": "Moldova, Republic of",
        "optionThree": "Italy",
        "optionFour": "Zambia",
        "correctAnswer": 3
    },
    {
        "id": 81,
        "question": "What country does this flag belong to?",
        "flag": "https://www.countryflags.io/JE/flat/64.png",
        "optionOne": "Liechtenstein",
        "optionTwo": "Jersey",
        "optionThree": "Nauru",
        "optionFour": "Andorra",
        "correctAnswer": 2
    },
    {
        "id": 82,
        "question": "What country does this flag belong to?",
        "flag": "https://www.countryflags.io/JM/flat/64.png",
        "optionOne": "Bolivia",
        "optionTwo": "Jamaica",
        "optionThree": "Czech Republic",
        "optionFour": "C\u00c3\u00b4te D'Ivoire",
        "correctAnswer": 2
    },
    {
        "id": 83,
        "question": "What country does this flag belong to?",
        "flag": "https://www.countryflags.io/JO/flat/64.png",
        "optionOne": "Liberia",
        "optionTwo": "Niue",
        "optionThree": "Jordan",
        "optionFour": "Korea, Republic of",
        "correctAnswer": 3
    },
    {
        "id": 84,
        "question": "What country does this flag belong to?",
        "flag": "https://www.countryflags.io/JP/flat/64.png",
        "optionOne": "Japan",
        "optionTwo": "Austria",
        "optionThree": "Bermuda",
        "optionFour": "Spain",
        "correctAnswer": 1
    },
    {
        "id": 85,
        "question": "What country does this flag belong to?",
        "flag": "https://www.countryflags.io/KE/flat/64.png",
        "optionOne": "Korea, Republic of",
        "optionTwo": "Mauritania",
        "optionThree": "Iraq",
        "optionFour": "Kenya",
        "correctAnswer": 4
    },
    {
        "id": 86,
        "question": "What country does this flag belong to?",
        "flag": "https://www.countryflags.io/KG/flat/64.png",
        "optionOne": "Iran, Islamic Republic Of",
        "optionTwo": "Austria",
        "optionThree": "Denmark",
        "optionFour": "Kyrgyzstan",
        "correctAnswer": 4
    },
    {
        "id": 87,
        "question": "What country does this flag belong to?",
        "flag": "https://www.countryflags.io/KH/flat/64.png",
        "optionOne": "Cambodia",
        "optionTwo": "Cyprus",
        "optionThree": "Dominican Republic",
        "optionFour": "\u00c3\u2026land Islands",
        "correctAnswer": 1
    },
    {
        "id": 88,
        "question": "What country does this flag belong to?",
        "flag": "https://www.countryflags.io/KI/flat/64.png",
        "optionOne": "Ecuador",
        "optionTwo": "Cambodia",
        "optionThree": "Kiribati",
        "optionFour": "Mexico",
        "correctAnswer": 3
    },
    {
        "id": 89,
        "question": "What country does this flag belong to?",
        "flag": "https://www.countryflags.io/KM/flat/64.png",
        "optionOne": "Comoros",
        "optionTwo": "Belarus",
        "optionThree": "Austria",
        "optionFour": "India",
        "correctAnswer": 1
    },
    {
        "id": 90,
        "question": "What country does this flag belong to?",
        "flag": "https://www.countryflags.io/KN/flat/64.png",
        "optionOne": "Northern Mariana Islands",
        "optionTwo": "Saint Kitts And Nevis",
        "optionThree": "Lebanon",
        "optionFour": "Cameroon",
        "correctAnswer": 2
    },
    {
        "id": 91,
        "question": "What country does this flag belong to?",
        "flag": "https://www.countryflags.io/KP/flat/64.png",
        "optionOne": "Korea, Democratic People's Republic Of",
        "optionTwo": "Liechtenstein",
        "optionThree": "Malawi",
        "optionFour": "Liberia",
        "correctAnswer": 1
    },
    {
        "id": 92,
        "question": "What country does this flag belong to?",
        "flag": "https://www.countryflags.io/KR/flat/64.png",
        "optionOne": "Mexico",
        "optionTwo": "Afghanistan",
        "optionThree": "Botswana",
        "optionFour": "Korea, Republic of",
        "correctAnswer": 4
    },
    {
        "id": 93,
        "question": "What country does this flag belong to?",
        "flag": "https://www.countryflags.io/KW/flat/64.png",
        "optionOne": "Kuwait",
        "optionTwo": "Central African Republic",
        "optionThree": "Eritrea",
        "optionFour": "Luxembourg",
        "correctAnswer": 1
    },
    {
        "id": 94,
        "question": "What country does this flag belong to?",
        "flag": "https://www.countryflags.io/KY/flat/64.png",
        "optionOne": "Italy",
        "optionTwo": "Yemen",
        "optionThree": "Martinique",
        "optionFour": "Cayman Islands",
        "correctAnswer": 4
    },
    {
        "id": 95,
        "question": "What country does this flag belong to?",
        "flag": "https://www.countryflags.io/KZ/flat/64.png",
        "optionOne": "Western Sahara",
        "optionTwo": "Belize",
        "optionThree": "Kazakhstan",
        "optionFour": "Ethiopia",
        "correctAnswer": 3
    },
    {
        "id": 96,
        "question": "What country does this flag belong to?",
        "flag": "https://www.countryflags.io/LA/flat/64.png",
        "optionOne": "Angola",
        "optionTwo": "Spain",
        "optionThree": "Isle of Man",
        "optionFour": "Lao People's Democratic Republic",
        "correctAnswer": 4
    },
    {
        "id": 97,
        "question": "What country does this flag belong to?",
        "flag": "https://www.countryflags.io/LB/flat/64.png",
        "optionOne": "Lao People's Democratic Republic",
        "optionTwo": "Lebanon",
        "optionThree": "Canada",
        "optionFour": "Namibia",
        "correctAnswer": 2
    },
    {
        "id": 98,
        "question": "What country does this flag belong to?",
        "flag": "https://www.countryflags.io/LC/flat/64.png",
        "optionOne": "Ecuador",
        "optionTwo": "Isle of Man",
        "optionThree": "Maldives",
        "optionFour": "Saint Lucia",
        "correctAnswer": 4
    },
    {
        "id": 99,
        "question": "What country does this flag belong to?",
        "flag": "https://www.countryflags.io/LI/flat/64.png",
        "optionOne": "Moldova, Republic of",
        "optionTwo": "Saint Lucia",
        "optionThree": "Liechtenstein",
        "optionFour": "Jersey",
        "correctAnswer": 3
    },
    {
        "id": 100,
        "question": "What country does this flag belong to?",
        "flag": "https://www.countryflags.io/LK/flat/64.png",
        "optionOne": "Sri Lanka",
        "optionTwo": "Barbados",
        "optionThree": "Marshall Islands",
        "optionFour": "Norway",
        "correctAnswer": 1
    },
    {
        "id": 101,
        "question": "What country does this flag belong to?",
        "flag": "https://www.countryflags.io/LR/flat/64.png",
        "optionOne": "Netherlands",
        "optionTwo": "Kenya",
        "optionThree": "Liberia",
        "optionFour": "Mongolia",
        "correctAnswer": 3
    },
    {
        "id": 102,
        "question": "What country does this flag belong to?",
        "flag": "https://www.countryflags.io/LS/flat/64.png",
        "optionOne": "Lesotho",
        "optionTwo": "Northern Mariana Islands",
        "optionThree": "Yemen",
        "optionFour": "Lithuania",
        "correctAnswer": 1
    },
    {
        "id": 103,
        "question": "What country does this flag belong to?",
        "flag": "https://www.countryflags.io/LT/flat/64.png",
        "optionOne": "Lithuania",
        "optionTwo": "Congo",
        "optionThree": "Spain",
        "optionFour": "Anguilla",
        "correctAnswer": 1
    },
    {
        "id": 104,
        "question": "What country does this flag belong to?",
        "flag": "https://www.countryflags.io/LU/flat/64.png",
        "optionOne": "Mozambique",
        "optionTwo": "Bangladesh",
        "optionThree": "Brazil",
        "optionFour": "Luxembourg",
        "correctAnswer": 4
    },
    {
        "id": 105,
        "question": "What country does this flag belong to?",
        "flag": "https://www.countryflags.io/LV/flat/64.png",
        "optionOne": "Costa Rica",
        "optionTwo": "Mauritius",
        "optionThree": "Christmas Island",
        "optionFour": "Latvia",
        "correctAnswer": 4
    },
    {
        "id": 106,
        "question": "What country does this flag belong to?",
        "flag": "https://www.countryflags.io/LY/flat/64.png",
        "optionOne": "Chile",
        "optionTwo": "Zimbabwe",
        "optionThree": "Cameroon",
        "optionFour": "Libya",
        "correctAnswer": 4
    },
    {
        "id": 107,
        "question": "What country does this flag belong to?",
        "flag": "https://www.countryflags.io/MA/flat/64.png",
        "optionOne": "Cook Islands",
        "optionTwo": "Burundi",
        "optionThree": "Morocco",
        "optionFour": "Algeria",
        "correctAnswer": 3
    },
    {
        "id": 108,
        "question": "What country does this flag belong to?",
        "flag": "https://www.countryflags.io/MC/flat/64.png",
        "optionOne": "Nigeria",
        "optionTwo": "China",
        "optionThree": "Nauru",
        "optionFour": "Monaco",
        "correctAnswer": 4
    },
    {
        "id": 109,
        "question": "What country does this flag belong to?",
        "flag": "https://www.countryflags.io/MD/flat/64.png",
        "optionOne": "Moldova, Republic of",
        "optionTwo": "Norway",
        "optionThree": "Cambodia",
        "optionFour": "Malawi",
        "correctAnswer": 1
    },
    {
        "id": 110,
        "question": "What country does this flag belong to?",
        "flag": "https://www.countryflags.io/ME/flat/64.png",
        "optionOne": "Nauru",
        "optionTwo": "Montenegro",
        "optionThree": "Australia",
        "optionFour": "Brazil",
        "correctAnswer": 2
    },
    {
        "id": 111,
        "question": "What country does this flag belong to?",
        "flag": "https://www.countryflags.io/MF/flat/64.png",
        "optionOne": "Niue",
        "optionTwo": "Saint Martin",
        "optionThree": "Cyprus",
        "optionFour": "Egypt",
        "correctAnswer": 2
    },
    {
        "id": 112,
        "question": "What country does this flag belong to?",
        "flag": "https://www.countryflags.io/MG/flat/64.png",
        "optionOne": "Cayman Islands",
        "optionTwo": "Mali",
        "optionThree": "Madagascar",
        "optionFour": "Indonesia",
        "correctAnswer": 3
    },
    {
        "id": 113,
        "question": "What country does this flag belong to?",
        "flag": "https://www.countryflags.io/MH/flat/64.png",
        "optionOne": "Belgium",
        "optionTwo": "Liberia",
        "optionThree": "United Arab Emirates",
        "optionFour": "Marshall Islands",
        "correctAnswer": 4
    },
    {
        "id": 114,
        "question": "What country does this flag belong to?",
        "flag": "https://www.countryflags.io/MK/flat/64.png",
        "optionOne": "Albania",
        "optionTwo": "Macedonia, the Former Yugoslav Republic Of",
        "optionThree": "Armenia",
        "optionFour": "Benin",
        "correctAnswer": 2
    },
    {
        "id": 115,
        "question": "What country does this flag belong to?",
        "flag": "https://www.countryflags.io/ML/flat/64.png",
        "optionOne": "Brunei Darussalam",
        "optionTwo": "Afghanistan",
        "optionThree": "Bhutan",
        "optionFour": "Mali",
        "correctAnswer": 4
    },
    {
        "id": 116,
        "question": "What country does this flag belong to?",
        "flag": "https://www.countryflags.io/MM/flat/64.png",
        "optionOne": "Canada",
        "optionTwo": "Italy",
        "optionThree": "Myanmar",
        "optionFour": "Nauru",
        "correctAnswer": 3
    },
    {
        "id": 117,
        "question": "What country does this flag belong to?",
        "flag": "https://www.countryflags.io/MN/flat/64.png",
        "optionOne": "Chile",
        "optionTwo": "Mongolia",
        "optionThree": "Bosnia and Herzegovina",
        "optionFour": "United Arab Emirates",
        "correctAnswer": 2
    },
    {
        "id": 118,
        "question": "What country does this flag belong to?",
        "flag": "https://www.countryflags.io/MO/flat/64.png",
        "optionOne": "Belgium",
        "optionTwo": "Botswana",
        "optionThree": "Macao",
        "optionFour": "Korea, Democratic People's Republic Of",
        "correctAnswer": 3
    },
    {
        "id": 119,
        "question": "What country does this flag belong to?",
        "flag": "https://www.countryflags.io/MP/flat/64.png",
        "optionOne": "Libya",
        "optionTwo": "Northern Mariana Islands",
        "optionThree": "Montserrat",
        "optionFour": "Nicaragua",
        "correctAnswer": 2
    },
    {
        "id": 120,
        "question": "What country does this flag belong to?",
        "flag": "https://www.countryflags.io/MQ/flat/64.png",
        "optionOne": "Latvia",
        "optionTwo": "Czech Republic",
        "optionThree": "Myanmar",
        "optionFour": "Martinique",
        "correctAnswer": 4
    },
    {
        "id": 121,
        "question": "What country does this flag belong to?",
        "flag": "https://www.countryflags.io/MR/flat/64.png",
        "optionOne": "Cyprus",
        "optionTwo": "Algeria",
        "optionThree": "Saint Martin",
        "optionFour": "Mauritania",
        "correctAnswer": 4
    },
    {
        "id": 122,
        "question": "What country does this flag belong to?",
        "flag": "https://www.countryflags.io/MS/flat/64.png",
        "optionOne": "Isle of Man",
        "optionTwo": "Montserrat",
        "optionThree": "Mongolia",
        "optionFour": "Estonia",
        "correctAnswer": 2
    },
    {
        "id": 123,
        "question": "What country does this flag belong to?",
        "flag": "https://www.countryflags.io/MT/flat/64.png",
        "optionOne": "Lithuania",
        "optionTwo": "Brazil",
        "optionThree": "Malta",
        "optionFour": "Estonia",
        "correctAnswer": 3
    },
    {
        "id": 124,
        "question": "What country does this flag belong to?",
        "flag": "https://www.countryflags.io/MU/flat/64.png",
        "optionOne": "Azerbaijan",
        "optionTwo": "Martinique",
        "optionThree": "Norway",
        "optionFour": "Mauritius",
        "correctAnswer": 4
    },
    {
        "id": 125,
        "question": "What country does this flag belong to?",
        "flag": "https://www.countryflags.io/MV/flat/64.png",
        "optionOne": "Nauru",
        "optionTwo": "Burkina Faso",
        "optionThree": "Maldives",
        "optionFour": "Lebanon",
        "correctAnswer": 3
    },
    {
        "id": 126,
        "question": "What country does this flag belong to?",
        "flag": "https://www.countryflags.io/MW/flat/64.png",
        "optionOne": "Spain",
        "optionTwo": "Malawi",
        "optionThree": "Kenya",
        "optionFour": "Malawi",
        "correctAnswer": 2
    },
    {
        "id": 127,
        "question": "What country does this flag belong to?",
        "flag": "https://www.countryflags.io/MX/flat/64.png",
        "optionOne": "Mexico",
        "optionTwo": "Cook Islands",
        "optionThree": "Colombia",
        "optionFour": "Chile",
        "correctAnswer": 1
    },
    {
        "id": 128,
        "question": "What country does this flag belong to?",
        "flag": "https://www.countryflags.io/MY/flat/64.png",
        "optionOne": "Norfolk Island",
        "optionTwo": "Jersey",
        "optionThree": "Nigeria",
        "optionFour": "Malaysia",
        "correctAnswer": 4
    },
    {
        "id": 129,
        "question": "What country does this flag belong to?",
        "flag": "https://www.countryflags.io/MZ/flat/64.png",
        "optionOne": "Mozambique",
        "optionTwo": "United Arab Emirates",
        "optionThree": "Comoros",
        "optionFour": "Colombia",
        "correctAnswer": 1
    },
    {
        "id": 130,
        "question": "What country does this flag belong to?",
        "flag": "https://www.countryflags.io/NA/flat/64.png",
        "optionOne": "Antigua and Barbuda",
        "optionTwo": "Cameroon",
        "optionThree": "Namibia",
        "optionFour": "Niue",
        "correctAnswer": 3
    },
    {
        "id": 131,
        "question": "What country does this flag belong to?",
        "flag": "https://www.countryflags.io/NC/flat/64.png",
        "optionOne": "Mauritania",
        "optionTwo": "Bahamas",
        "optionThree": "New Caledonia",
        "optionFour": "Bulgaria",
        "correctAnswer": 3
    },
    {
        "id": 132,
        "question": "What country does this flag belong to?",
        "flag": "https://www.countryflags.io/NE/flat/64.png",
        "optionOne": "South Africa",
        "optionTwo": "Germany",
        "optionThree": "Niger",
        "optionFour": "Spain",
        "correctAnswer": 3
    },
    {
        "id": 133,
        "question": "What country does this flag belong to?",
        "flag": "https://www.countryflags.io/NF/flat/64.png",
        "optionOne": "Central African Republic",
        "optionTwo": "Italy",
        "optionThree": "Norfolk Island",
        "optionFour": "Bangladesh",
        "correctAnswer": 3
    },
    {
        "id": 134,
        "question": "What country does this flag belong to?",
        "flag": "https://www.countryflags.io/NG/flat/64.png",
        "optionOne": "Mexico",
        "optionTwo": "Australia",
        "optionThree": "Saint Lucia",
        "optionFour": "Nigeria",
        "correctAnswer": 4
    },
    {
        "id": 135,
        "question": "What country does this flag belong to?",
        "flag": "https://www.countryflags.io/NI/flat/64.png",
        "optionOne": "Nicaragua",
        "optionTwo": "Norfolk Island",
        "optionThree": "Niue",
        "optionFour": "Luxembourg",
        "correctAnswer": 1
    },
    {
        "id": 136,
        "question": "What country does this flag belong to?",
        "flag": "https://www.countryflags.io/NL/flat/64.png",
        "optionOne": "Netherlands",
        "optionTwo": "Christmas Island",
        "optionThree": "South Africa",
        "optionFour": "Korea, Republic of",
        "correctAnswer": 1
    },
    {
        "id": 137,
        "question": "What country does this flag belong to?",
        "flag": "https://www.countryflags.io/NO/flat/64.png",
        "optionOne": "Congo",
        "optionTwo": "Norway",
        "optionThree": "Mali",
        "optionFour": "Belgium",
        "correctAnswer": 2
    },
    {
        "id": 138,
        "question": "What country does this flag belong to?",
        "flag": "https://www.countryflags.io/NP/flat/64.png",
        "optionOne": "Nepal",
        "optionTwo": "Nauru",
        "optionThree": "Burundi",
        "optionFour": "Bolivia",
        "correctAnswer": 1
    },
    {
        "id": 139,
        "question": "What country does this flag belong to?",
        "flag": "https://www.countryflags.io/NR/flat/64.png",
        "optionOne": "Nauru",
        "optionTwo": "Norfolk Island",
        "optionThree": "Angola",
        "optionFour": "Zimbabwe",
        "correctAnswer": 1
    },
    {
        "id": 140,
        "question": "What country does this flag belong to?",
        "flag": "https://www.countryflags.io/NU/flat/64.png",
        "optionOne": "Cocos (Keeling) Islands",
        "optionTwo": "Niue",
        "optionThree": "Martinique",
        "optionFour": "Sri Lanka",
        "correctAnswer": 2
    },
    {
        "id": 141,
        "question": "What country does this flag belong to?",
        "flag": "https://www.countryflags.io/YE/flat/64.png",
        "optionOne": "South Africa",
        "optionTwo": "Kyrgyzstan",
        "optionThree": "Korea, Democratic People's Republic Of",
        "optionFour": "Yemen",
        "correctAnswer": 4
    },
    {
        "id": 142,
        "question": "What country does this flag belong to?",
        "flag": "https://www.countryflags.io/YT/flat/64.png",
        "optionOne": "Albania",
        "optionTwo": "Azerbaijan",
        "optionThree": "Mayotte",
        "optionFour": "Mozambique",
        "correctAnswer": 3
    },
    {
        "id": 143,
        "question": "What country does this flag belong to?",
        "flag": "https://www.countryflags.io/ZA/flat/64.png",
        "optionOne": "Kuwait",
        "optionTwo": "South Africa",
        "optionThree": "Antarctica",
        "optionFour": "South Africa",
        "correctAnswer": 4
    },
    {
        "id": 144,
        "question": "What country does this flag belong to?",
        "flag": "https://www.countryflags.io/ZM/flat/64.png",
        "optionOne": "Anguilla",
        "optionTwo": "Zambia",
        "optionThree": "Saint Barth\u00c3\u00a9lemy",
        "optionFour": "Aruba",
        "correctAnswer": 2
    },
    {
        "id": 145,
        "question": "What country does this flag belong to?",
        "flag": "https://www.countryflags.io/ZW/flat/64.png",
        "optionOne": "Central African Republic",
        "optionTwo": "Zimbabwe",
        "optionThree": "Liberia",
        "optionFour": "Japan",
        "correctAnswer": 2
    }
]